ofxstatement_newb-0.0.3-py3.8-nspkg.pth
ofxstatement/plugins/newb.py
ofxstatement_newb-0.0.3.dist-info/LICENSE
ofxstatement_newb-0.0.3.dist-info/METADATA
ofxstatement_newb-0.0.3.dist-info/WHEEL
ofxstatement_newb-0.0.3.dist-info/entry_points.txt
ofxstatement_newb-0.0.3.dist-info/namespace_packages.txt
ofxstatement_newb-0.0.3.dist-info/top_level.txt
ofxstatement_newb-0.0.3.dist-info/zip-safe
ofxstatement_newb-0.0.3.dist-info/RECORD
