Metadata-Version: 2.1
Name: ofxstatement-newb
Version: 0.0.3
Summary: NewB plugin for ofxstatement
Home-page: https://github.com/SDaron/ofxstatement-be-newb
Author: Simon Daron
Author-email: UNKNOWN
License: GPLv3
Keywords: ofx,banking,statement
Platform: UNKNOWN
Classifier: Development Status :: 3 - Alpha
Classifier: Programming Language :: Python :: 3
Classifier: Natural Language :: English
Classifier: Topic :: Office/Business :: Financial :: Accounting
Classifier: Topic :: Utilities
Classifier: Environment :: Console
Classifier: Operating System :: OS Independent
Classifier: License :: OSI Approved :: GNU General Public License v3 (GPLv3)
Requires-Dist: ofxstatement
